jgt_tools/__init__.py
jgt_tools/check_version.py
jgt_tools/data/defaults.csv
jgt_tools/docs/__init__.py
jgt_tools/docs/build_docs.py
jgt_tools/docs/sample_conf.py
jgt_tools/env_setup.py
jgt_tools/run_tests.py
jgt_tools/self_check.py
jgt_tools/utils.py
jgt_tools-0.6.1.dist-info/METADATA
jgt_tools-0.6.1.dist-info/WHEEL
jgt_tools-0.6.1.dist-info/entry_points.txt
jgt_tools-0.6.1.dist-info/RECORD
