Metadata-Version: 2.1
Name: jgt-tools
Version: 0.6.1
Summary: A collection of tools for commmon package scripts
Home-page: https://jolly-good-toolbelt.github.io/jgt_tools/
License: MIT
Author: Brad Brown
Author-email: brad@bradsbrown.com
Requires-Python: >=3.8.1,<4.0.0
Classifier: License :: OSI Approved :: MIT License
Classifier: Programming Language :: Python :: 3
Classifier: Programming Language :: Python :: 3.9
Classifier: Programming Language :: Python :: 3.10
Classifier: Programming Language :: Python :: 3.11
Provides-Extra: build-docs
Provides-Extra: env-setup
Provides-Extra: run-tests
Requires-Dist: ghp-import (>=0.5.5) ; extra == "build-docs"
Requires-Dist: pre-commit (>=1.15) ; extra == "env-setup"
Requires-Dist: pytest (>=5.0) ; extra == "run-tests"
Requires-Dist: setuptools
Requires-Dist: sphinx (>=3.1.2) ; extra == "build-docs"
Requires-Dist: sphinx-rtd-theme (>=0.5.0) ; extra == "build-docs"
Requires-Dist: tomli (>=2.0.1,<3.0.0)
Project-URL: Documentation, https://jolly-good-toolbelt.github.io/jgt_tools/
Project-URL: Repository, https://github.com/jolly-good-toolbelt/jgt_tools
